odoo/addons/sale_order_blanket_order/README.rst
odoo/addons/sale_order_blanket_order/__init__.py
odoo/addons/sale_order_blanket_order/__manifest__.py
odoo/addons/sale_order_blanket_order/hooks.py
odoo/addons/sale_order_blanket_order/data/ir_cron.xml
odoo/addons/sale_order_blanket_order/i18n/fr.po
odoo/addons/sale_order_blanket_order/i18n/it.po
odoo/addons/sale_order_blanket_order/i18n/sale_order_blanket_order.pot
odoo/addons/sale_order_blanket_order/models/__init__.py
odoo/addons/sale_order_blanket_order/models/product_template.py
odoo/addons/sale_order_blanket_order/models/res_company.py
odoo/addons/sale_order_blanket_order/models/res_config_settings.py
odoo/addons/sale_order_blanket_order/models/sale_order.py
odoo/addons/sale_order_blanket_order/models/sale_order_line.py
odoo/addons/sale_order_blanket_order/models/stock_move.py
odoo/addons/sale_order_blanket_order/models/stock_rule.py
odoo/addons/sale_order_blanket_order/readme/CONTEXT.md
odoo/addons/sale_order_blanket_order/readme/CONTRIBUTORS.md
odoo/addons/sale_order_blanket_order/readme/CREDITS.md
odoo/addons/sale_order_blanket_order/readme/DESCRIPTION.md
odoo/addons/sale_order_blanket_order/readme/USAGE.md
odoo/addons/sale_order_blanket_order/security/ir.model.access.csv
odoo/addons/sale_order_blanket_order/static/description/icon.png
odoo/addons/sale_order_blanket_order/static/description/index.html
odoo/addons/sale_order_blanket_order/tests/__init__.py
odoo/addons/sale_order_blanket_order/tests/common.py
odoo/addons/sale_order_blanket_order/tests/test_sale_blanket_order.py
odoo/addons/sale_order_blanket_order/tests/test_sale_call_off_order.py
odoo/addons/sale_order_blanket_order/tests/test_sale_normal_order.py
odoo/addons/sale_order_blanket_order/tests/test_sale_order_deliver_remaining_wizard.py
odoo/addons/sale_order_blanket_order/views/product_template.xml
odoo/addons/sale_order_blanket_order/views/res_config_settings.xml
odoo/addons/sale_order_blanket_order/views/sale_order.xml
odoo_addon_sale_order_blanket_order-16.0.1.1.0.2.dist-info/METADATA
odoo_addon_sale_order_blanket_order-16.0.1.1.0.2.dist-info/WHEEL
odoo_addon_sale_order_blanket_order-16.0.1.1.0.2.dist-info/top_level.txt
odoo_addon_sale_order_blanket_order-16.0.1.1.0.2.dist-info/RECORD
